teemup.py
teemup-1.2.1.dist-info/LICENSE
teemup-1.2.1.dist-info/METADATA
teemup-1.2.1.dist-info/WHEEL
teemup-1.2.1.dist-info/RECORD
