Metadata-Version: 2.1
Name: teemup
Version: 1.2.1
Summary: If Meetup didn't become a walled garden, the world wouldn't need Teemup
License: MIT
Author: Honza Javorek
Author-email: mail@honzajavorek.cz
Requires-Python: >=3.11,<4.0
Classifier: License :: OSI Approved :: MIT License
Classifier: Programming Language :: Python :: 3
Classifier: Programming Language :: Python :: 3.11
Classifier: Programming Language :: Python :: 3.12
Classifier: Programming Language :: Python :: 3.13
Requires-Dist: cssselect (==1.2.0)
Requires-Dist: lxml (==5.3.0)
